{"viewLastModified": 1504898817, "rowsUpdatedBy": "9e4n-uys4", "hideFromCatalog": false, "displayType": "table", "publicationStage": "published", "id": "34sw-6tcv", "rights": ["read"], "license": {"termsLink": "http://opendatacommons.org/licenses/pddl/1.0/", "name": "Open Data Commons Public Domain Dedication and License"}, "provenance": "official", "publicationGroup": 14450809, "tableAuthor": {"screenName": "A. Fuller", "displayName": "A. Fuller", "id": "9e4n-uys4", "type": "interactive"}, "rowsUpdatedAt": 1504897986, "columns": [{"cachedContents": {"top": [{"count": 20, "item": "OP"}], "null": 1, "non_null": 110827, "largest": "OP", "smallest": "OP"}, "format": {}, "position": 2, "name": "Agency", "tableColumnId": 53030936, "width": 172, "renderTypeName": "text", "id": 319362380, "dataTypeName": "text", "fieldName": "agency"}, {"cachedContents": {"top": [{"count": 20, "item": "2016-07-31T23:45:50"}, {"count": 19, "item": "2016-07-31T23:50:54"}, {"count": 18, "item": "2016-07-31T23:56:29"}, {"count": 17, "item": "2016-07-31T23:57:31"}], "null": 1, "non_null": 110827, "largest": "2016-07-31T23:57:31", "smallest": "2016-01-01T00:00:57"}, "format": {"view": "default_date_time"}, "position": 3, "name": "Create Time", "tableColumnId": 53030937, "width": 232, "renderTypeName": "calendar_date", "id": 319362381, "dataTypeName": "calendar_date", "fieldName": "create_time"}, {"cachedContents": {"top": [{"count": 20, "item": "W AV&INTERNATIONAL BLVD    "}, {"count": 19, "item": "W INTERNATIONAL BLVD    "}, {"count": 18, "item": "WB INTERNATIONAL BLVD    "}, {"count": 17, "item": "WB LAKESHORE AV    "}, {"count": 16, "item": "WB TELEGRAPH AV    "}, {"count": 15, "item": "WB ST&SAN PABLO AV   "}, {"count": 14, "item": "WB GRAND AV    "}, {"count": 13, "item": "WB FRESNO ST    "}, {"count": 12, "item": "WB DR&SERRAMAR DR    "}, {"count": 11, "item": "WB ST&FALLON ST    "}, {"count": 10, "item": "WB FRUITVALE AV    "}, {"count": 9, "item": "WB PIEDMONT AV    "}, {"count": 8, "item": "WB HIGH ST    "}, {"count": 7, "item": "WB AV&INTERNATIONAL BLVD    "}, {"count": 6, "item": "WB AV&SANTA CLARA AV   "}, {"count": 5, "item": "WB AV&FOOTHILL BLVD    "}, {"count": 4, "item": "WB HARRISON ST    "}, {"count": 3, "item": "WB 86TH AV    "}, {"count": 2, "item": "WB ADELINE ST    "}, {"count": 1, "item": "WB FOOTHILL BLVD    "}], "null": 0, "non_null": 110828, "largest": " ZORAH ST    ", "smallest": "      "}, "format": {}, "position": 4, "name": "Location", "tableColumnId": 53030938, "width": 196, "renderTypeName": "text", "id": 319362382, "dataTypeName": "text", "fieldName": "location"}, {"cachedContents": {"top": [{"count": 20, "item": "P1"}, {"count": 19, "item": "P3"}, {"count": 18, "item": "P2"}, {"count": 17, "item": "POU"}, {"count": 16, "item": "PCW"}, {"count": 15, "item": "TEC"}, {"count": 14, "item": "JLS"}, {"count": 13, "item": "WAG"}], "null": 1, "non_null": 110827, "largest": "WAG", "smallest": "JLS"}, "format": {}, "position": 5, "name": "Area Id", "tableColumnId": 53030939, "width": 184, "renderTypeName": "text", "id": 319362383, "dataTypeName": "text", "fieldName": "area_id"}, {"cachedContents": {"top": [{"count": 20, "item": "04X"}, {"count": 19, "item": "23X"}, {"count": 18, "item": "07X"}, {"count": 17, "item": "08X"}, {"count": 16, "item": "30X"}, {"count": 15, "item": "26Y"}, {"count": 14, "item": "19X"}, {"count": 13, "item": "30Y"}, {"count": 12, "item": "03X"}, {"count": 11, "item": "27Y"}, {"count": 10, "item": "34X"}, {"count": 9, "item": "29X"}, {"count": 8, "item": "06X"}, {"count": 7, "item": "25X"}, {"count": 6, "item": "20X"}, {"count": 5, "item": "03Y"}, {"count": 4, "item": "35X"}, {"count": 3, "item": "27X"}, {"count": 2, "item": "31Y"}, {"count": 1, "item": "33X"}], "null": 581, "non_null": 110247, "largest": "PDT2", "smallest": "01X"}, "format": {}, "position": 6, "name": "Beat", "tableColumnId": 53030940, "width": 148, "renderTypeName": "text", "id": 319362384, "dataTypeName": "text", "fieldName": "beat"}, {"cachedContents": {"top": [{"count": 20, "item": "2"}, {"count": 19, "item": "1"}], "average": "1.778438467160529", "smallest": "1", "null": 1, "non_null": 110827, "largest": "2", "sum": "197099"}, "format": {"groupSeparator": ",", "decimalSeparator": "."}, "position": 7, "name": "Priority", "tableColumnId": 53030941, "width": 196, "renderTypeName": "number", "id": 319362385, "dataTypeName": "number", "fieldName": "priority"}, {"cachedContents": {"top": [{"count": 20, "item": "933R"}, {"count": 19, "item": "415"}, {"count": 18, "item": "242"}, {"count": 17, "item": "10851"}, {"count": 16, "item": "WELCK"}, {"count": 15, "item": "415C"}, {"count": 14, "item": "912"}, {"count": 13, "item": "SECCK"}, {"count": 12, "item": "5150"}, {"count": 11, "item": "911H"}, {"count": 10, "item": "243E"}, {"count": 9, "item": "949"}, {"count": 8, "item": "HAZ"}, {"count": 7, "item": "415GS"}, {"count": 6, "item": "415FC"}, {"count": 5, "item": "901A"}, {"count": 4, "item": "211"}, {"count": 3, "item": "245"}, {"count": 2, "item": "415CU"}, {"count": 1, "item": "933MA"}], "null": 1, "non_null": 110827, "largest": "YELALT", "smallest": "10801"}, "format": {}, "position": 8, "name": "Incident Type Id", "tableColumnId": 53030942, "width": 292, "renderTypeName": "text", "id": 319362386, "dataTypeName": "text", "fieldName": "incident_type_id"}, {"cachedContents": {"top": [{"count": 20, "item": "ALARM-RINGER"}, {"count": 19, "item": "BATTERY"}, {"count": 18, "item": "STOLEN VEHICLE"}, {"count": 17, "item": "DISTURBING THE PEACE"}, {"count": 16, "item": "WELFARE CHECK -- CHE"}, {"count": 15, "item": "415 UNKNOWN"}, {"count": 14, "item": "SECURITY CHECK"}, {"count": 13, "item": "415 FAMILY"}, {"count": 12, "item": "MENTALLY ILL"}, {"count": 11, "item": "911 HANG-UP"}, {"count": 10, "item": "SUSPICIOUS VEHICLE"}, {"count": 9, "item": "BATTERY ON CO-HABITA"}, {"count": 8, "item": "SUSPICIOUS PERSON"}, {"count": 7, "item": "HAZARDOUS SITUATION/"}, {"count": 6, "item": "415 GUNSHOTS"}, {"count": 5, "item": "415 FIRE CRACKERS"}, {"count": 4, "item": "ROBBERY"}, {"count": 3, "item": "ALARM-MANUALLY ACTIV"}, {"count": 2, "item": "SIDESHOW"}, {"count": 1, "item": "VEHICLE COLLISION-PE"}], "null": 1, "non_null": 110827, "largest": "YELLOW ALERT AT THE", "smallest": "21235 MOTORSCOOTER"}, "format": {}, "position": 9, "name": "Incident Type Description", "tableColumnId": 53030943, "width": 400, "renderTypeName": "text", "id": 319362387, "dataTypeName": "text", "fieldName": "incident_type_description"}, {"cachedContents": {"top": [{"count": 20, "item": "LOP160731000892"}, {"count": 19, "item": "LOP160731000893"}, {"count": 18, "item": "LOP160731000895"}, {"count": 17, "item": "LOP160731000897"}], "null": 1, "non_null": 110827, "largest": "LOP160731000897", "smallest": "LOP160101000003"}, "format": {}, "position": 10, "name": "Event Number", "tableColumnId": 53030944, "width": 244, "renderTypeName": "text", "id": 319362388, "dataTypeName": "text", "fieldName": "event_number"}, {"cachedContents": {"top": [{"count": 20, "item": "2016-07-31T23:58:03"}, {"count": 19, "item": "2016-08-01T00:08:00"}, {"count": 18, "item": "2016-08-01T01:33:31"}, {"count": 17, "item": "2016-08-01T00:16:16"}], "null": 1, "non_null": 110827, "largest": "2017-02-02T11:10:10", "smallest": "2016-01-01T00:11:13"}, "format": {"view": "default_date_time"}, "position": 11, "name": "Closed Time", "tableColumnId": 53030945, "width": 232, "renderTypeName": "calendar_date", "id": 319362389, "dataTypeName": "calendar_date", "fieldName": "closed_time"}], "publicationAppendEnabled": false, "newBackend": true, "numberOfComments": 0, "oid": 26758988, "publicationDate": 1504898817, "licenseId": "PDDL", "owner": {"screenName": "A. Fuller", "displayName": "A. Fuller", "id": "9e4n-uys4", "type": "interactive"}, "grants": [{"flags": ["public"], "inherited": false, "type": "viewer"}], "viewType": "tabular", "totalTimesRated": 0, "query": {}, "category": "Public Services", "tableId": 14450809, "flags": ["default", "restorable", "restorePossibleForType"], "locale": "en_US", "hideFromDataJson": false, "createdAt": 1504897898, "indexUpdatedAt": 1504898743, "name": "Records For 2016", "viewCount": 93, "averageRating": 0, "metadata": {"availableDisplayTypes": ["table", "fatrow", "page"], "renderTypeConfig": {"visible": {"table": true}}}, "downloadCount": 32, "description": "PRR 20055 crime statistics"}